battery.py
charts.py
cli.py
cpu.py
disks.py
files.py
tools.py
viztree.py
vizexdf/files.py
vizexdu/battery.py
vizexdu/charts.py
vizexdu/cpu.py
vizexdu/disks.py
vizex-2.1.0.dist-info/LICENSE
vizex-2.1.0.dist-info/METADATA
vizex-2.1.0.dist-info/WHEEL
vizex-2.1.0.dist-info/entry_points.txt
vizex-2.1.0.dist-info/top_level.txt
vizex-2.1.0.dist-info/RECORD
