Metadata-Version: 2.1
Name: vizex
Version: 2.1.0
Summary: UNIX/Linux Terminal program to graphically display the disk space usage and/or directory data
Home-page: https://github.com/bexxmodd/vizex
Author: Beka Modebadze
Author-email: bexx.modd@gmail.com
License: UNKNOWN
Platform: UNKNOWN
Classifier: Programming Language :: Python :: 3.8
Classifier: Programming Language :: Python :: 3.9
Classifier: License :: OSI Approved :: MIT License
Classifier: Operating System :: POSIX
Requires-Python: >=3.8
License-File: LICENSE
Requires-Dist: attrs (>=20.2.0)
Requires-Dist: build (>=0.3.1.post1)
Requires-Dist: click (>=7.1.2)
Requires-Dist: colored (>=1.4.2)
Requires-Dist: iniconfig (>=1.0.1)
Requires-Dist: isort (>=5.8.0)
Requires-Dist: lazy-object-proxy (>=1.6.0)
Requires-Dist: mccabe (>=0.6.1)
Requires-Dist: numpy (>=1.19.2)
Requires-Dist: packaging (>=20.4)
Requires-Dist: pandas (>=1.1.3)
Requires-Dist: pluggy (>=0.13.1)
Requires-Dist: psutil (>=5.7.2)
Requires-Dist: py (>=1.9.0)
Requires-Dist: pytest (>=6.1.1)
Requires-Dist: python-dateutil (>=2.8.1)
Requires-Dist: python-magic (>=0.4.18)
Requires-Dist: pytz (>=2020.1)
Requires-Dist: six (>=1.15.0)
Requires-Dist: tabulate (>=0.8.7)
Requires-Dist: toml (>=0.10.1)
